{"nodes": [{"modular": 1, "label": "Heron's formula", "id": "Heron's formula", "viz": {"size": 11.428572, "position": {"y": 65.54643, "x": -478.23926, "z": 0.0}}, "Out-Degree": 0, "In-Degree": 2, "degree": 2}, {"modular": 0, "label": "expoentiation", "id": "expoentiation", "viz": {"size": 10.714286, "position": {"y": 440.58746, "x": 972.04034, "z": 0.0}}, "Out-Degree": 0, "In-Degree": 1, "degree": 1}, {"modular": 1, "label": "compute intersection", "id": "compute intersection", "viz": {"size": 12.857143, "position": {"y": -740.173, "x": -246.53035, "z": 0.0}}, "Out-Degree": 0, "In-Degree": 4, "degree": 4}, {"modular": 1, "label": "Quadratic formula", "id": "Quadratic formula", "viz": {"size": 11.428572, "position": {"y": -307.34833, "x": 640.0904, "z": 0.0}}, "Out-Degree": 0, "In-Degree": 2, "degree": 2}, {"modular": 0, "label": "tangent(circle)", "id": "tangent(circle)", "viz": {"size": 10.714286, "position": {"y": 594.855, "x": -301.58472, "z": 0.0}}, "Out-Degree": 0, "In-Degree": 1, "degree": 1}, {"modular": 0, "label": "equilateral triangle", "id": "equilateral triangle", "viz": {"size": 11.428572, "position": {"y": 512.7816, "x": -885.04047, "z": 0.0}}, "Out-Degree": 0, "In-Degree": 2, "degree": 2}, {"modular": 0, "label": "power function", "id": "power function", "viz": {"size": 10.714286, "position": {"y": -585.05133, "x": -111.29106, "z": 0.0}}, "Out-Degree": 0, "In-Degree": 1, "degree": 1}, {"modular": 0, "label": "monotonicity", "id": "monotonicity", "viz": {"size": 12.857143, "position": {"y": -668.1974, "x": 10.841054, "z": 0.0}}, "Out-Degree": 1, "In-Degree": 3, "degree": 4}, {"modular": 0, "label": "coprime numbers", "id": "coprime numbers", "viz": {"size": 10.714286, "position": {"y": -2.469756, "x": 1374.5123, "z": 0.0}}, "Out-Degree": 0, "In-Degree": 1, "degree": 1}, {"modular": 0, "label": "imaginary number", "id": "imaginary number", "viz": {"size": 10.714286, "position": {"y": 668.7312, "x": 839.1774, "z": 0.0}}, "Out-Degree": 0, "In-Degree": 1, "degree": 1}, {"modular": 0, "label": "checking the primality", "id": "checking the primality", "viz": {"size": 12.857143, "position": {"y": -30.019228, "x": 1499.6537, "z": 0.0}}, "Out-Degree": 3, "In-Degree": 1, "degree": 4}, {"modular": 0, "label": "Differential calculus", "id": "Differential calculus", "viz": {"size": 12.142857, "position": {"y": -503.23343, "x": -50.92603, "z": 0.0}}, "Out-Degree": 0, "In-Degree": 3, "degree": 3}, {"modular": 0, "label": "Incircle and excircles of a triangle", "id": "Incircle and excircles of a triangle", "viz": {"size": 11.428572, "position": {"y": 414.77545, "x": -425.34573, "z": 0.0}}, "Out-Degree": 0, "In-Degree": 2, "degree": 2}, {"modular": 0, "label": "irrational number", "id": "irrational number", "viz": {"size": 11.428572, "position": {"y": 544.4435, "x": 493.48895, "z": 0.0}}, "Out-Degree": 1, "In-Degree": 1, "degree": 2}, {"modular": 0, "label": "cartesian coordinate system", "id": "cartesian coordinate system", "viz": {"size": 14.285714, "position": {"y": -874.1747, "x": 78.61277, "z": 0.0}}, "Out-Degree": 5, "In-Degree": 1, "degree": 6}, {"modular": 0, "label": "quadratic function", "id": "quadratic function", "viz": {"size": 18.571428, "position": {"y": -699.0061, "x": 224.89497, "z": 0.0}}, "Out-Degree": 11, "In-Degree": 1, "degree": 12}, {"modular": 0, "label": "Golden rectangle", "id": "Golden rectangle", "viz": {"size": 11.428572, "position": {"y": 1249.1515, "x": 334.4754, "z": 0.0}}, "Out-Degree": 0, "In-Degree": 2, "degree": 2}, {"modular": 0, "label": "secant", "id": "secant", "viz": {"size": 10.714286, "position": {"y": 587.2427, "x": -243.92671, "z": 0.0}}, "Out-Degree": 0, "In-Degree": 1, "degree": 1}, {"modular": 0, "label": "Inequation", "id": "Inequation", "viz": {"size": 13.571428, "position": {"y": -115.86356, "x": -68.9408, "z": 0.0}}, "Out-Degree": 5, "In-Degree": 0, "degree": 5}, {"modular": 0, "label": "lengths of a point on the perpendicular bisector to each vertex are equal", "id": "lengths of a point on the perpendicular bisector to each vertex are equal", "viz": {"size": 10.714286, "position": {"y": 257.6185, "x": -815.2204, "z": 0.0}}, "Out-Degree": 0, "In-Degree": 1, "degree": 1}, {"modular": 0, "label": "Transformation (function)", "id": "Transformation (function)", "viz": {"size": 15.0, "position": {"y": -947.8056, "x": -84.1145, "z": 0.0}}, "Out-Degree": 6, "In-Degree": 1, "degree": 7}, {"modular": 0, "label": "substitution", "id": "substitution", "viz": {"size": 10.714286, "position": {"y": -590.80786, "x": -196.54115, "z": 0.0}}, "Out-Degree": 0, "In-Degree": 1, "degree": 1}, {"modular": 0, "label": "subset", "id": "subset", "viz": {"size": 10.714286, "position": {"y": -1177.3505, "x": -228.996, "z": 0.0}}, "Out-Degree": 0, "In-Degree": 1, "degree": 1}, {"modular": 0, "label": "diagrammatic sketch", "id": "diagrammatic sketch", "viz": {"size": 10.714286, "position": {"y": -671.57367, "x": 270.05383, "z": 0.0}}, "Out-Degree": 0, "In-Degree": 1, "degree": 1}, {"modular": 0, "label": "mid-segment line", "id": "mid-segment line", "viz": {"size": 10.714286, "position": {"y": 207.36472, "x": -582.9567, "z": 0.0}}, "Out-Degree": 0, "In-Degree": 1, "degree": 1}, {"modular": 0, "label": "Corresponding angles", "id": "Corresponding angles", "viz": {"size": 10.714286, "position": {"y": -594.41986, "x": -998.0705, "z": 0.0}}, "Out-Degree": 0, "In-Degree": 1, "degree": 1}, {"modular": 0, "label": "square", "id": "square", "viz": {"size": 14.285714, "position": {"y": 1439.9066, "x": 74.07084, "z": 0.0}}, "Out-Degree": 5, "In-Degree": 1, "degree": 6}, {"modular": 0, "label": "FOIL method", "id": "FOIL method", "viz": {"size": 10.714286, "position": {"y": 193.93436, "x": 875.75104, "z": 0.0}}, "Out-Degree": 0, "In-Degree": 1, "degree": 1}, {"modular": 0, "label": "Parallel (geometry)", "id": "Parallel (geometry)", "viz": {"size": 11.428572, "position": {"y": -1010.8817, "x": -769.0081, "z": 0.0}}, "Out-Degree": 1, "In-Degree": 1, "degree": 2}, {"modular": 1, "label": "right triangle altitude theorem", "id": "right triangle altitude theorem", "viz": {"size": 10.714286, "position": {"y": -89.01302, "x": -627.1924, "z": 0.0}}, "Out-Degree": 0, "In-Degree": 1, "degree": 1}, {"modular": 0, "label": "Parallelogram", "id": "Parallelogram", "viz": {"size": 10.714286, "position": {"y": 888.45, "x": -344.11667, "z": 0.0}}, "Out-Degree": 0, "In-Degree": 1, "degree": 1}, {"modular": 0, "label": "discriminant of the quadratic equation", "id": "discriminant of the quadratic equation", "viz": {"size": 10.714286, "position": {"y": -104.22938, "x": 640.61926, "z": 0.0}}, "Out-Degree": 0, "In-Degree": 1, "degree": 1}, {"modular": 0, "label": "acute triangle", "id": "acute triangle", "viz": {"size": 10.714286, "position": {"y": 215.3025, "x": -628.78723, "z": 0.0}}, "Out-Degree": 0, "In-Degree": 1, "degree": 1}, {"modular": 0, "label": "standard form", "id": "standard form", "viz": {"size": 10.714286, "position": {"y": -739.18005, "x": 242.78627, "z": 0.0}}, "Out-Degree": 0, "In-Degree": 1, "degree": 1}, {"modular": 1, "label": "compute coordinates of symmetric points", "id": "compute coordinates of symmetric points", "viz": {"size": 10.714286, "position": {"y": -921.4744, "x": 105.7807, "z": 0.0}}, "Out-Degree": 0, "In-Degree": 1, "degree": 1}, {"modular": 0, "label": "one variable linear equation", "id": "one variable linear equation", "viz": {"size": 10.714286, "position": {"y": -271.9478, "x": 281.8038, "z": 0.0}}, "Out-Degree": 0, "In-Degree": 1, "degree": 1}, {"modular": 0, "label": "sine", "id": "sine", "viz": {"size": 11.428572, "position": {"y": -412.0402, "x": -497.82452, "z": 0.0}}, "Out-Degree": 1, "In-Degree": 1, "degree": 2}, {"modular": 0, "label": "prime factorization", "id": "prime factorization", "viz": {"size": 10.714286, "position": {"y": 1068.9092, "x": 961.9395, "z": 0.0}}, "Out-Degree": 0, "In-Degree": 1, "degree": 1}, {"modular": 0, "label": "binomial", "id": "binomial", "viz": {"size": 12.142857, "position": {"y": 359.39722, "x": 952.69604, "z": 0.0}}, "Out-Degree": 2, "In-Degree": 1, "degree": 3}, {"modular": 0, "label": "cotangent", "id": "cotangent", "viz": {"size": 11.428572, "position": {"y": -373.61127, "x": -568.2624, "z": 0.0}}, "Out-Degree": 1, "In-Degree": 1, "degree": 2}, {"modular": 0, "label": "cyclic", "id": "cyclic", "viz": {"size": 11.428572, "position": {"y": 1440.5145, "x": 125.33343, "z": 0.0}}, "Out-Degree": 0, "In-Degree": 2, "degree": 2}, {"modular": 0, "label": "isosceles trapezoid", "id": "isosceles trapezoid", "viz": {"size": 10.714286, "position": {"y": 1115.0962, "x": -196.32854, "z": 0.0}}, "Out-Degree": 0, "In-Degree": 1, "degree": 1}, {"modular": 0, "label": "Zero of a function", "id": "Zero of a function", "viz": {"size": 12.142857, "position": {"y": -619.27826, "x": 479.9764, "z": 0.0}}, "Out-Degree": 2, "In-Degree": 1, "degree": 3}, {"modular": 0, "label": "angle", "id": "angle", "viz": {"size": 18.571428, "position": {"y": -553.9207, "x": -998.5865, "z": 0.0}}, "Out-Degree": 12, "In-Degree": 0, "degree": 12}, {"modular": 0, "label": "Gaussian integer", "id": "Gaussian integer", "viz": {"size": 10.714286, "position": {"y": 646.66754, "x": 826.3477, "z": 0.0}}, "Out-Degree": 0, "In-Degree": 1, "degree": 1}, {"modular": 1, "label": "vertical angle theorem", "id": "vertical angle theorem", "viz": {"size": 10.714286, "position": {"y": -725.0767, "x": -832.4101, "z": 0.0}}, "Out-Degree": 0, "In-Degree": 1, "degree": 1}, {"modular": 0, "label": "Parallel postulate", "id": "Parallel postulate", "viz": {"size": 10.714286, "position": {"y": -1022.4294, "x": -792.63403, "z": 0.0}}, "Out-Degree": 0, "In-Degree": 1, "degree": 1}, {"modular": 0, "label": "Reflectional symmetry", "id": "Reflectional symmetry", "viz": {"size": 11.428572, "position": {"y": 620.0083, "x": -221.17398, "z": 0.0}}, "Out-Degree": 0, "In-Degree": 2, "degree": 2}, {"modular": 0, "label": "SSS (Side-Side-Side)", "id": "SSS (Side-Side-Side)", "viz": {"size": 10.714286, "position": {"y": 369.32617, "x": -809.54626, "z": 0.0}}, "Out-Degree": 0, "In-Degree": 1, "degree": 1}, {"modular": 0, "label": "lehmer's gcd algorithm", "id": "lehmer's gcd algorithm", "viz": {"size": 10.714286, "position": {"y": 1110.3666, "x": 986.3584, "z": 0.0}}, "Out-Degree": 0, "In-Degree": 1, "degree": 1}, {"modular": 0, "label": "lateral surface area", "id": "lateral surface area", "viz": {"size": 11.428572, "position": {"y": -104.85561, "x": -328.37244, "z": 0.0}}, "Out-Degree": 0, "In-Degree": 2, "degree": 2}, {"modular": 0, "label": "Affine transformation", "id": "Affine transformation", "viz": {"size": 10.714286, "position": {"y": -990.17944, "x": -56.828094, "z": 0.0}}, "Out-Degree": 0, "In-Degree": 1, "degree": 1}, {"modular": 1, "label": "Japanese theorem for cyclic quadrilaterals", "id": "Japanese theorem for cyclic quadrilaterals", "viz": {"size": 10.714286, "position": {"y": 1340.3201, "x": 148.68895, "z": 0.0}}, "Out-Degree": 0, "In-Degree": 1, "degree": 1}, {"modular": 0, "label": "rational number", "id": "rational number", "viz": {"size": 11.428572, "position": {"y": 367.59177, "x": 859.0496, "z": 0.0}}, "Out-Degree": 1, "In-Degree": 1, "degree": 2}, {"modular": 0, "label": "Cone", "id": "Cone", "viz": {"size": 11.428572, "position": {"y": -79.9461, "x": -323.014, "z": 0.0}}, "Out-Degree": 2, "In-Degree": 0, "degree": 2}, {"modular": 1, "label": "complex number", "id": "complex number", "viz": {"size": 15.0, "position": {"y": 641.90717, "x": 863.45917, "z": 0.0}}, "Out-Degree": 7, "In-Degree": 0, "degree": 7}, {"modular": 1, "label": "isopermetric theorem", "id": "isopermetric theorem", "viz": {"size": 10.714286, "position": {"y": 1383.6992, "x": 187.1568, "z": 0.0}}, "Out-Degree": 0, "In-Degree": 1, "degree": 1}, {"modular": 0, "label": "symmetry", "id": "symmetry", "viz": {"size": 11.428572, "position": {"y": -721.14294, "x": 107.5707, "z": 0.0}}, "Out-Degree": 0, "In-Degree": 2, "degree": 2}, {"modular": 0, "label": "Quadrilateral", "id": "Quadrilateral", "viz": {"size": 12.857143, "position": {"y": 858.9131, "x": -338.88657, "z": 0.0}}, "Out-Degree": 3, "In-Degree": 1, "degree": 4}, {"modular": 0, "label": "Miller\u2013Rabin primality test", "id": "Miller\u2013Rabin primality test", "viz": {"size": 10.714286, "position": {"y": -4.254327, "x": 1505.2925, "z": 0.0}}, "Out-Degree": 0, "In-Degree": 1, "degree": 1}, {"modular": 0, "label": "complement", "id": "complement", "viz": {"size": 10.714286, "position": {"y": -1159.6619, "x": -197.34624, "z": 0.0}}, "Out-Degree": 0, "In-Degree": 1, "degree": 1}, {"modular": 1, "label": "binomial theorem", "id": "binomial theorem", "viz": {"size": 11.428572, "position": {"y": 283.61792, "x": 928.2997, "z": 0.0}}, "Out-Degree": 0, "In-Degree": 2, "degree": 2}, {"modular": 1, "label": "compute poles", "id": "compute poles", "viz": {"size": 10.714286, "position": {"y": -426.80173, "x": -38.4591, "z": 0.0}}, "Out-Degree": 1, "In-Degree": 0, "degree": 1}, {"modular": 1, "label": "Menelaus's theorem", "id": "Menelaus's theorem", "viz": {"size": 10.714286, "position": {"y": 288.5, "x": -542.4996, "z": 0.0}}, "Out-Degree": 0, "In-Degree": 1, "degree": 1}, {"modular": 0, "label": "factorization", "id": "factorization", "viz": {"size": 14.285714, "position": {"y": 222.26193, "x": 891.7876, "z": 0.0}}, "Out-Degree": 3, "In-Degree": 3, "degree": 6}, {"modular": 0, "label": "slope-intercept form", "id": "slope-intercept form", "viz": {"size": 10.714286, "position": {"y": -733.91327, "x": -187.30559, "z": 0.0}}, "Out-Degree": 0, "In-Degree": 1, "degree": 1}, {"modular": 0, "label": "Goldbach's conjecture", "id": "Goldbach's conjecture", "viz": {"size": 10.714286, "position": {"y": -17.256094, "x": 1352.8633, "z": 0.0}}, "Out-Degree": 0, "In-Degree": 1, "degree": 1}, {"modular": 0, "label": "Interior angles on the same side", "id": "Interior angles on the same side", "viz": {"size": 10.714286, "position": {"y": -589.9674, "x": -1022.26843, "z": 0.0}}, "Out-Degree": 0, "In-Degree": 1, "degree": 1}, {"modular": 0, "label": "quadratic equation", "id": "quadratic equation", "viz": {"size": 13.571428, "position": {"y": -126.104774, "x": 625.98425, "z": 0.0}}, "Out-Degree": 4, "In-Degree": 1, "degree": 5}, {"modular": 0, "label": "inscribed angle", "id": "inscribed angle", "viz": {"size": 10.714286, "position": {"y": 533.8669, "x": -229.44867, "z": 0.0}}, "Out-Degree": 0, "In-Degree": 1, "degree": 1}, {"modular": 0, "label": "Trapezoid", "id": "Trapezoid", "viz": {"size": 12.142857, "position": {"y": 1116.2537, "x": -176.44176, "z": 0.0}}, "Out-Degree": 2, "In-Degree": 1, "degree": 3}, {"modular": 1, "label": "Fundamental theorem of calculus", "id": "Fundamental theorem of calculus", "viz": {"size": 11.428572, "position": {"y": -302.69653, "x": -203.425, "z": 0.0}}, "Out-Degree": 0, "In-Degree": 2, "degree": 2}, {"modular": 0, "label": "binary gcd algorithm", "id": "binary gcd algorithm", "viz": {"size": 10.714286, "position": {"y": 1053.6064, "x": 995.36255, "z": 0.0}}, "Out-Degree": 0, "In-Degree": 1, "degree": 1}, {"modular": 0, "label": "altitude", "id": "altitude", "viz": {"size": 10.714286, "position": {"y": 321.5394, "x": -613.37317, "z": 0.0}}, "Out-Degree": 0, "In-Degree": 1, "degree": 1}, {"modular": 0, "label": "Point reflection", "id": "Point reflection", "viz": {"size": 10.714286, "position": {"y": 514.6206, "x": -271.14474, "z": 0.0}}, "Out-Degree": 0, "In-Degree": 1, "degree": 1}, {"modular": 1, "label": "Ceva's theorem", "id": "Ceva's theorem", "viz": {"size": 10.714286, "position": {"y": 232.8096, "x": -644.2714, "z": 0.0}}, "Out-Degree": 0, "In-Degree": 1, "degree": 1}, {"modular": 0, "label": "isogonal", "id": "isogonal", "viz": {"size": 11.428572, "position": {"y": 1422.2188, "x": 112.792816, "z": 0.0}}, "Out-Degree": 0, "In-Degree": 2, "degree": 2}, {"modular": 0, "label": "Perpendicular", "id": "Perpendicular", "viz": {"size": 10.714286, "position": {"y": -991.405, "x": -694.2175, "z": 0.0}}, "Out-Degree": 0, "In-Degree": 1, "degree": 1}, {"modular": 0, "label": "Difference of two squares", "id": "Difference of two squares", "viz": {"size": 12.142857, "position": {"y": 337.26428, "x": 935.2879, "z": 0.0}}, "Out-Degree": 0, "In-Degree": 3, "degree": 3}, {"modular": 0, "label": "Bisection method", "id": "Bisection method", "viz": {"size": 10.714286, "position": {"y": -481.2665, "x": 651.03735, "z": 0.0}}, "Out-Degree": 0, "In-Degree": 1, "degree": 1}, {"modular": 0, "label": "tangent", "id": "tangent", "viz": {"size": 11.428572, "position": {"y": -408.40952, "x": -544.4739, "z": 0.0}}, "Out-Degree": 1, "In-Degree": 1, "degree": 2}, {"modular": 0, "label": "positive and negative property", "id": "positive and negative property", "viz": {"size": 10.714286, "position": {"y": -772.82855, "x": -174.43005, "z": 0.0}}, "Out-Degree": 0, "In-Degree": 1, "degree": 1}, {"modular": 0, "label": "System of Linear Inequalities with one unknown", "id": "System of Linear Inequalities with one unknown", "viz": {"size": 10.714286, "position": {"y": -86.46387, "x": -53.9793, "z": 0.0}}, "Out-Degree": 0, "In-Degree": 1, "degree": 1}, {"modular": 0, "label": "Homothetic transformation", "id": "Homothetic transformation", "viz": {"size": 10.714286, "position": {"y": -968.40356, "x": -53.00669, "z": 0.0}}, "Out-Degree": 0, "In-Degree": 1, "degree": 1}, {"modular": 0, "label": "addition", "id": "addition", "viz": {"size": 12.142857, "position": {"y": 601.0151, "x": 922.77563, "z": 0.0}}, "Out-Degree": 0, "In-Degree": 3, "degree": 3}, {"modular": 0, "label": "multiplication", "id": "multiplication", "viz": {"size": 12.857143, "position": {"y": 573.3826, "x": 908.6401, "z": 0.0}}, "Out-Degree": 1, "In-Degree": 3, "degree": 4}, {"modular": 0, "label": "law of tangents", "id": "law of tangents", "viz": {"size": 10.714286, "position": {"y": -432.72156, "x": -567.214, "z": 0.0}}, "Out-Degree": 0, "In-Degree": 1, "degree": 1}, {"modular": 0, "label": "divisor", "id": "divisor", "viz": {"size": 11.428572, "position": {"y": 909.8389, "x": 895.6298, "z": 0.0}}, "Out-Degree": 1, "In-Degree": 1, "degree": 2}, {"modular": 0, "label": "Venn diagram", "id": "Venn diagram", "viz": {"size": 10.714286, "position": {"y": -1146.8436, "x": -252.11894, "z": 0.0}}, "Out-Degree": 0, "In-Degree": 1, "degree": 1}, {"modular": 0, "label": "induction", "id": "induction", "viz": {"size": 10.714286, "position": {"y": -169.71909, "x": 1371.1101, "z": 0.0}}, "Out-Degree": 0, "In-Degree": 1, "degree": 1}, {"modular": 0, "label": "B\u00e9zout's identity", "id": "B\u00e9zout's identity", "viz": {"size": 10.714286, "position": {"y": -86.67199, "x": 1430.0707, "z": 0.0}}, "Out-Degree": 1, "In-Degree": 0, "degree": 1}, {"modular": 0, "label": "Degree (angle)", "id": "Degree (angle)", "viz": {"size": 10.714286, "position": {"y": -530.41626, "x": -970.49365, "z": 0.0}}, "Out-Degree": 0, "In-Degree": 1, "degree": 1}, {"modular": 0, "label": "System of 2 linear equations with 2 unknowns", "id": "System of 2 linear equations with 2 unknowns", "viz": {"size": 12.142857, "position": {"y": -248.22533, "x": 354.23096, "z": 0.0}}, "Out-Degree": 2, "In-Degree": 1, "degree": 3}, {"modular": 0, "label": "center of incircle", "id": "center of incircle", "viz": {"size": 10.714286, "position": {"y": 185.81464, "x": -788.03326, "z": 0.0}}, "Out-Degree": 0, "In-Degree": 1, "degree": 1}, {"modular": 0, "label": "features of coordinates in each quadrant", "id": "features of coordinates in each quadrant", "viz": {"size": 10.714286, "position": {"y": -899.78864, "x": 102.6809, "z": 0.0}}, "Out-Degree": 0, "In-Degree": 1, "degree": 1}, {"modular": 0, "label": "periodicity", "id": "periodicity", "viz": {"size": 10.714286, "position": {"y": -341.31625, "x": -466.5231, "z": 0.0}}, "Out-Degree": 0, "In-Degree": 1, "degree": 1}, {"modular": 0, "label": "Intersection", "id": "Intersection", "viz": {"size": 10.714286, "position": {"y": -1176.4513, "x": -209.42137, "z": 0.0}}, "Out-Degree": 0, "In-Degree": 1, "degree": 1}, {"modular": 0, "label": "Rotation (mathematics)", "id": "Rotation (mathematics)", "viz": {"size": 10.714286, "position": {"y": -970.97955, "x": -111.90277, "z": 0.0}}, "Out-Degree": 0, "In-Degree": 1, "degree": 1}, {"modular": 0, "label": "Intersection (Euclidean geometry)", "id": "Intersection (Euclidean geometry)", "viz": {"size": 12.142857, "position": {"y": -819.1947, "x": -602.7294, "z": 0.0}}, "Out-Degree": 2, "In-Degree": 1, "degree": 3}, {"modular": 0, "label": "real number", "id": "real number", "viz": {"size": 12.142857, "position": {"y": 520.3446, "x": 733.15686, "z": 0.0}}, "Out-Degree": 2, "In-Degree": 1, "degree": 3}, {"modular": 0, "label": "vertical angles", "id": "vertical angles", "viz": {"size": 12.142857, "position": {"y": -706.9054, "x": -819.5634, "z": 0.0}}, "Out-Degree": 1, "In-Degree": 2, "degree": 3}, {"modular": 0, "label": "maximum and minimum value", "id": "maximum and minimum value", "viz": {"size": 10.714286, "position": {"y": -663.5532, "x": 248.45546, "z": 0.0}}, "Out-Degree": 0, "In-Degree": 1, "degree": 1}, {"modular": 0, "label": "central angle", "id": "central angle", "viz": {"size": 10.714286, "position": {"y": 569.42725, "x": -227.45576, "z": 0.0}}, "Out-Degree": 0, "In-Degree": 1, "degree": 1}, {"modular": 0, "label": "Row reduction", "id": "Row reduction", "viz": {"size": 10.714286, "position": {"y": -220.69885, "x": 370.81995, "z": 0.0}}, "Out-Degree": 0, "In-Degree": 1, "degree": 1}, {"modular": 1, "label": "British flag theorem", "id": "British flag theorem", "viz": {"size": 10.714286, "position": {"y": 1344.1283, "x": 170.16844, "z": 0.0}}, "Out-Degree": 0, "In-Degree": 1, "degree": 1}, {"modular": 0, "label": "linear function (calculus)", "id": "linear function (calculus)", "viz": {"size": 15.0, "position": {"y": -735.99695, "x": -153.08365, "z": 0.0}}, "Out-Degree": 6, "In-Degree": 1, "degree": 7}, {"modular": 0, "label": "acute angles", "id": "acute angles", "viz": {"size": 10.714286, "position": {"y": -513.9661, "x": -1018.63104, "z": 0.0}}, "Out-Degree": 0, "In-Degree": 1, "degree": 1}, {"modular": 0, "label": "translational property", "id": "translational property", "viz": {"size": 10.714286, "position": {"y": -771.3256, "x": -152.85553, "z": 0.0}}, "Out-Degree": 0, "In-Degree": 1, "degree": 1}, {"modular": 0, "label": "Pi", "id": "Pi", "viz": {"size": 11.428572, "position": {"y": 560.4808, "x": 254.93066, "z": 0.0}}, "Out-Degree": 0, "In-Degree": 2, "degree": 2}, {"modular": 0, "label": "linear ineqality with one unknown", "id": "linear ineqality with one unknown", "viz": {"size": 10.714286, "position": {"y": -103.38223, "x": -38.391212, "z": 0.0}}, "Out-Degree": 0, "In-Degree": 1, "degree": 1}, {"modular": 0, "label": "inverse proportional form", "id": "inverse proportional form", "viz": {"size": 10.714286, "position": {"y": -755.6277, "x": -12.687589, "z": 0.0}}, "Out-Degree": 0, "In-Degree": 1, "degree": 1}, {"modular": 0, "label": "Radian", "id": "Radian", "viz": {"size": 10.714286, "position": {"y": -513.1316, "x": -995.68176, "z": 0.0}}, "Out-Degree": 0, "In-Degree": 1, "degree": 1}, {"modular": 0, "label": "opening direction and scale of a function", "id": "opening direction and scale of a function", "viz": {"size": 10.714286, "position": {"y": -717.8282, "x": 261.9778, "z": 0.0}}, "Out-Degree": 0, "In-Degree": 1, "degree": 1}, {"modular": 0, "label": "subtraction", "id": "subtraction", "viz": {"size": 12.142857, "position": {"y": 586.5362, "x": 940.6125, "z": 0.0}}, "Out-Degree": 0, "In-Degree": 3, "degree": 3}, {"modular": 0, "label": "Circle", "id": "Circle", "viz": {"size": 22.142857, "position": {"y": 556.81146, "x": -275.67877, "z": 0.0}}, "Out-Degree": 17, "In-Degree": 0, "degree": 17}, {"modular": 0, "label": "Algebraic fraction", "id": "Algebraic fraction", "viz": {"size": 12.857143, "position": {"y": 662.2056, "x": 921.49146, "z": 0.0}}, "Out-Degree": 4, "In-Degree": 0, "degree": 4}, {"modular": 0, "label": "euclidean algorithm", "id": "euclidean algorithm", "viz": {"size": 10.714286, "position": {"y": 1095.8177, "x": 960.7493, "z": 0.0}}, "Out-Degree": 0, "In-Degree": 1, "degree": 1}, {"modular": 0, "label": "area only related to k", "id": "area only related to k", "viz": {"size": 10.714286, "position": {"y": -761.90533, "x": -35.384212, "z": 0.0}}, "Out-Degree": 0, "In-Degree": 1, "degree": 1}, {"modular": 0, "label": "scalene triangle", "id": "scalene triangle", "viz": {"size": 10.714286, "position": {"y": 218.8361, "x": -559.65967, "z": 0.0}}, "Out-Degree": 0, "In-Degree": 1, "degree": 1}, {"modular": 1, "label": "Theorem of the gnomon", "id": "Theorem of the gnomon", "viz": {"size": 10.714286, "position": {"y": 1333.9739, "x": 42.766045, "z": 0.0}}, "Out-Degree": 0, "In-Degree": 1, "degree": 1}, {"modular": 1, "label": "prime number theorem", "id": "prime number theorem", "viz": {"size": 10.714286, "position": {"y": -41.263176, "x": 1350.3429, "z": 0.0}}, "Out-Degree": 0, "In-Degree": 1, "degree": 1}, {"modular": 0, "label": "division", "id": "division", "viz": {"size": 12.857143, "position": {"y": 808.7525, "x": 842.5027, "z": 0.0}}, "Out-Degree": 2, "In-Degree": 2, "degree": 4}, {"modular": 0, "label": "prime number", "id": "prime number", "viz": {"size": 16.428572, "position": {"y": -36.71832, "x": 1387.3036, "z": 0.0}}, "Out-Degree": 8, "In-Degree": 1, "degree": 9}, {"modular": 0, "label": "integer", "id": "integer", "viz": {"size": 12.142857, "position": {"y": 220.6313, "x": 998.0786, "z": 0.0}}, "Out-Degree": 2, "In-Degree": 1, "degree": 3}, {"modular": 0, "label": "supplementary angle", "id": "supplementary angle", "viz": {"size": 10.714286, "position": {"y": -567.2572, "x": -1124.3772, "z": 0.0}}, "Out-Degree": 0, "In-Degree": 1, "degree": 1}, {"modular": 0, "label": "Inequality of arithmetic and geometric means", "id": "Inequality of arithmetic and geometric means", "viz": {"size": 11.428572, "position": {"y": -278.05713, "x": -55.684483, "z": 0.0}}, "Out-Degree": 0, "In-Degree": 2, "degree": 2}, {"modular": 0, "label": "quailateral", "id": "quailateral", "viz": {"size": 10.714286, "position": {"y": 1360.4891, "x": 184.17422, "z": 0.0}}, "Out-Degree": 0, "In-Degree": 1, "degree": 1}, {"modular": 0, "label": "inverse proportional function", "id": "inverse proportional function", "viz": {"size": 15.0, "position": {"y": -727.0503, "x": -38.08814, "z": 0.0}}, "Out-Degree": 6, "In-Degree": 1, "degree": 7}, {"modular": 0, "label": "Euler line", "id": "Euler line", "viz": {"size": 10.714286, "position": {"y": 264.5207, "x": -537.4447, "z": 0.0}}, "Out-Degree": 0, "In-Degree": 1, "degree": 1}, {"modular": 1, "label": "Alternate Segment Theorem", "id": "Alternate Segment Theorem", "viz": {"size": 10.714286, "position": {"y": 691.76996, "x": -267.3277, "z": 0.0}}, "Out-Degree": 0, "In-Degree": 1, "degree": 1}, {"modular": 0, "label": "AKS primality test", "id": "AKS primality test", "viz": {"size": 10.714286, "position": {"y": -25.309345, "x": 1525.8119, "z": 0.0}}, "Out-Degree": 0, "In-Degree": 1, "degree": 1}, {"modular": 0, "label": "Linear map", "id": "Linear map", "viz": {"size": 10.714286, "position": {"y": -1000.55145, "x": -79.62277, "z": 0.0}}, "Out-Degree": 0, "In-Degree": 1, "degree": 1}, {"modular": 0, "label": "isotoxal", "id": "isotoxal", "viz": {"size": 11.428572, "position": {"y": 1438.3599, "x": 19.105745, "z": 0.0}}, "Out-Degree": 0, "In-Degree": 2, "degree": 2}, {"modular": 1, "label": "Intersecting Chords Theorem", "id": "Intersecting Chords Theorem", "viz": {"size": 10.714286, "position": {"y": 666.72284, "x": -168.41432, "z": 0.0}}, "Out-Degree": 0, "In-Degree": 1, "degree": 1}, {"modular": 0, "label": "cosine", "id": "cosine", "viz": {"size": 11.428572, "position": {"y": -333.11874, "x": -550.7129, "z": 0.0}}, "Out-Degree": 1, "In-Degree": 1, "degree": 2}, {"modular": 0, "label": "multiple", "id": "multiple", "viz": {"size": 11.428572, "position": {"y": 547.69214, "x": 876.5567, "z": 0.0}}, "Out-Degree": 1, "In-Degree": 1, "degree": 2}, {"modular": 1, "label": "Bolzano's theorem", "id": "Bolzano's theorem", "viz": {"size": 11.428572, "position": {"y": -507.80652, "x": 689.92395, "z": 0.0}}, "Out-Degree": 0, "In-Degree": 2, "degree": 2}, {"modular": 1, "label": "fundamental theorem of arithmetic", "id": "fundamental theorem of arithmetic", "viz": {"size": 12.142857, "position": {"y": -141.60641, "x": 1393.7781, "z": 0.0}}, "Out-Degree": 1, "In-Degree": 2, "degree": 3}, {"modular": 0, "label": "area of the sector", "id": "area of the sector", "viz": {"size": 10.714286, "position": {"y": 519.9394, "x": -244.72142, "z": 0.0}}, "Out-Degree": 0, "In-Degree": 1, "degree": 1}, {"modular": 1, "label": "compute maximum or minimum", "id": "compute maximum or minimum", "viz": {"size": 12.857143, "position": {"y": -452.73526, "x": -58.038246, "z": 0.0}}, "Out-Degree": 2, "In-Degree": 2, "degree": 4}, {"modular": 1, "label": "euclid's theorem", "id": "euclid's theorem", "viz": {"size": 12.142857, "position": {"y": -60.239685, "x": 1422.0486, "z": 0.0}}, "Out-Degree": 0, "In-Degree": 3, "degree": 3}, {"modular": 0, "label": "Reflection", "id": "Reflection", "viz": {"size": 10.714286, "position": {"y": -980.545, "x": -78.25318, "z": 0.0}}, "Out-Degree": 0, "In-Degree": 1, "degree": 1}, {"modular": 0, "label": "median", "id": "median", "viz": {"size": 10.714286, "position": {"y": 310.5357, "x": -632.3882, "z": 0.0}}, "Out-Degree": 0, "In-Degree": 1, "degree": 1}, {"modular": 0, "label": "Equation", "id": "Equation", "viz": {"size": 14.285714, "position": {"y": -299.34055, "x": 271.92227, "z": 0.0}}, "Out-Degree": 5, "In-Degree": 1, "degree": 6}, {"modular": 0, "label": "obtuse angles", "id": "obtuse angles", "viz": {"size": 10.714286, "position": {"y": -526.5444, "x": -1035.4877, "z": 0.0}}, "Out-Degree": 0, "In-Degree": 1, "degree": 1}, {"modular": 0, "label": "exhaustion", "id": "exhaustion", "viz": {"size": 10.714286, "position": {"y": 1081.704, "x": 1017.4766, "z": 0.0}}, "Out-Degree": 0, "In-Degree": 1, "degree": 1}, {"modular": 0, "label": "length of the arc", "id": "length of the arc", "viz": {"size": 11.428572, "position": {"y": 565.4921, "x": 4.394076, "z": 0.0}}, "Out-Degree": 1, "In-Degree": 1, "degree": 2}, {"modular": 0, "label": "conditions on the sides", "id": "conditions on the sides", "viz": {"size": 11.428572, "position": {"y": 283.30276, "x": -639.8665, "z": 0.0}}, "Out-Degree": 0, "In-Degree": 2, "degree": 2}, {"modular": 1, "label": "compute line segment that parallel axes: big coordinates - small coordinates", "id": "compute line segment that parallel axes: big coordinates - small coordinates", "viz": {"size": 10.714286, "position": {"y": -904.2521, "x": 124.093834, "z": 0.0}}, "Out-Degree": 0, "In-Degree": 1, "degree": 1}, {"modular": 0, "label": "chord tangent angle", "id": "chord tangent angle", "viz": {"size": 11.428572, "position": {"y": 654.8172, "x": -273.65247, "z": 0.0}}, "Out-Degree": 1, "In-Degree": 1, "degree": 2}, {"modular": 0, "label": "Function (mathematics)", "id": "Function (mathematics)", "viz": {"size": 20.0, "position": {"y": -623.4794, "x": -100.89451, "z": 0.0}}, "Out-Degree": 13, "In-Degree": 1, "degree": 14}, {"modular": 0, "label": "Triangle inequality", "id": "Triangle inequality", "viz": {"size": 11.428572, "position": {"y": 77.930855, "x": -322.73212, "z": 0.0}}, "Out-Degree": 0, "In-Degree": 2, "degree": 2}, {"modular": 1, "label": "compute area", "id": "compute area", "viz": {"size": 14.285714, "position": {"y": -122.45847, "x": -363.11694, "z": 0.0}}, "Out-Degree": 3, "In-Degree": 3, "degree": 6}, {"modular": 0, "label": "ASA (Angle-Side-Angle)", "id": "ASA (Angle-Side-Angle)", "viz": {"size": 10.714286, "position": {"y": 396.76126, "x": -794.1599, "z": 0.0}}, "Out-Degree": 0, "In-Degree": 1, "degree": 1}, {"modular": 1, "label": "Intercept theorem", "id": "Intercept theorem", "viz": {"size": 10.714286, "position": {"y": 601.6957, "x": -988.0065, "z": 0.0}}, "Out-Degree": 0, "In-Degree": 1, "degree": 1}, {"modular": 0, "label": "Translation (geometry)", "id": "Translation (geometry)", "viz": {"size": 10.714286, "position": {"y": -989.53375, "x": -101.24851, "z": 0.0}}, "Out-Degree": 0, "In-Degree": 1, "degree": 1}, {"modular": 0, "label": "total surface area", "id": "total surface area", "viz": {"size": 11.428572, "position": {"y": -86.95773, "x": -348.49246, "z": 0.0}}, "Out-Degree": 0, "In-Degree": 2, "degree": 2}, {"modular": 0, "label": "circumcenter", "id": "circumcenter", "viz": {"size": 10.714286, "position": {"y": 276.80606, "x": -815.0094, "z": 0.0}}, "Out-Degree": 0, "In-Degree": 1, "degree": 1}, {"modular": 0, "label": "Extraneous and missing solutions", "id": "Extraneous and missing solutions", "viz": {"size": 10.714286, "position": {"y": -313.8811, "x": 356.6203, "z": 0.0}}, "Out-Degree": 0, "In-Degree": 1, "degree": 1}, {"modular": 0, "label": "cartesian product", "id": "cartesian product", "viz": {"size": 11.428572, "position": {"y": -900.1829, "x": -175.18634, "z": 0.0}}, "Out-Degree": 1, "In-Degree": 1, "degree": 2}, {"modular": 0, "label": "euclid's lemma", "id": "euclid's lemma", "viz": {"size": 10.714286, "position": {"y": -175.64493, "x": 1391.8037, "z": 0.0}}, "Out-Degree": 1, "In-Degree": 0, "degree": 1}, {"modular": 1, "label": "compute function expression", "id": "compute function expression", "viz": {"size": 11.428572, "position": {"y": -603.95337, "x": -167.51703, "z": 0.0}}, "Out-Degree": 1, "In-Degree": 1, "degree": 2}, {"modular": 0, "label": "regional property", "id": "regional property", "viz": {"size": 10.714286, "position": {"y": -734.3256, "x": -3.5205479, "z": 0.0}}, "Out-Degree": 0, "In-Degree": 1, "degree": 1}, {"modular": 0, "label": "Fraction equation", "id": "Fraction equation", "viz": {"size": 11.428572, "position": {"y": -310.19904, "x": 328.59213, "z": 0.0}}, "Out-Degree": 1, "In-Degree": 1, "degree": 2}, {"modular": 1, "label": "Pythagorean theorem", "id": "Pythagorean theorem", "viz": {"size": 11.428572, "position": {"y": -216.40201, "x": -556.9836, "z": 0.0}}, "Out-Degree": 0, "In-Degree": 2, "degree": 2}, {"modular": 0, "label": "coefficients of a polynomial", "id": "coefficients of a polynomial", "viz": {"size": 10.714286, "position": {"y": -663.6194, "x": 568.4138, "z": 0.0}}, "Out-Degree": 1, "In-Degree": 0, "degree": 1}, {"modular": 0, "label": "vertex form", "id": "vertex form", "viz": {"size": 10.714286, "position": {"y": -739.31506, "x": 265.35468, "z": 0.0}}, "Out-Degree": 0, "In-Degree": 1, "degree": 1}, {"modular": 0, "label": "Set (mathematics)", "id": "Set (mathematics)", "viz": {"size": 14.285714, "position": {"y": -1137.6073, "x": -221.46852, "z": 0.0}}, "Out-Degree": 6, "In-Degree": 0, "degree": 6}, {"modular": 0, "label": "Regular polygon", "id": "Regular polygon", "viz": {"size": 10.714286, "position": {"y": 647.6015, "x": -528.8183, "z": 0.0}}, "Out-Degree": 0, "In-Degree": 1, "degree": 1}, {"modular": 0, "label": "obtuse triangle", "id": "obtuse triangle", "viz": {"size": 10.714286, "position": {"y": 319.63354, "x": -573.5849, "z": 0.0}}, "Out-Degree": 0, "In-Degree": 1, "degree": 1}, {"modular": 1, "label": "Intermediate value theorem", "id": "Intermediate value theorem", "viz": {"size": 10.714286, "position": {"y": -515.3632, "x": 717.33246, "z": 0.0}}, "Out-Degree": 1, "In-Degree": 0, "degree": 1}, {"modular": 0, "label": "convex", "id": "convex", "viz": {"size": 13.571428, "position": {"y": 1342.6592, "x": 2.912858, "z": 0.0}}, "Out-Degree": 0, "In-Degree": 5, "degree": 5}, {"modular": 0, "label": "Line segment", "id": "Line segment", "viz": {"size": 11.428572, "position": {"y": -1039.8164, "x": -727.7455, "z": 0.0}}, "Out-Degree": 1, "In-Degree": 1, "degree": 2}, {"modular": 0, "label": "Polygon", "id": "Polygon", "viz": {"size": 12.857143, "position": {"y": 622.4235, "x": -503.36124, "z": 0.0}}, "Out-Degree": 4, "In-Degree": 0, "degree": 4}, {"modular": 1, "label": "compute the area of a polygon in a plane: cutting method", "id": "compute the area of a polygon in a plane: cutting method", "viz": {"size": 10.714286, "position": {"y": -914.0652, "x": 83.40866, "z": 0.0}}, "Out-Degree": 0, "In-Degree": 1, "degree": 1}, {"modular": 0, "label": "Integral", "id": "Integral", "viz": {"size": 11.428572, "position": {"y": -213.8824, "x": -279.86804, "z": 0.0}}, "Out-Degree": 2, "In-Degree": 0, "degree": 2}, {"modular": 0, "label": "Derivative", "id": "Derivative", "viz": {"size": 11.428572, "position": {"y": -395.86874, "x": -128.69208, "z": 0.0}}, "Out-Degree": 2, "In-Degree": 0, "degree": 2}, {"modular": 1, "label": "Completing the square", "id": "Completing the square", "viz": {"size": 10.714286, "position": {"y": -133.14531, "x": 652.11066, "z": 0.0}}, "Out-Degree": 0, "In-Degree": 1, "degree": 1}, {"modular": 0, "label": "union", "id": "union", "viz": {"size": 10.714286, "position": {"y": -1167.4185, "x": -245.90617, "z": 0.0}}, "Out-Degree": 0, "In-Degree": 1, "degree": 1}, {"modular": 0, "label": "SAS (Side-Angle-Side)", "id": "SAS (Side-Angle-Side)", "viz": {"size": 10.714286, "position": {"y": 389.02042, "x": -812.45447, "z": 0.0}}, "Out-Degree": 0, "In-Degree": 1, "degree": 1}, {"modular": 0, "label": "straight angle", "id": "straight angle", "viz": {"size": 11.428572, "position": {"y": -566.8155, "x": -1091.591, "z": 0.0}}, "Out-Degree": 1, "In-Degree": 1, "degree": 2}, {"modular": 0, "label": "supplementary angles", "id": "supplementary angles", "viz": {"size": 10.714286, "position": {"y": -571.53375, "x": -1036.7036, "z": 0.0}}, "Out-Degree": 0, "In-Degree": 1, "degree": 1}, {"modular": 1, "label": "compare value of functions", "id": "compare value of functions", "viz": {"size": 10.714286, "position": {"y": -593.1114, "x": -74.62516, "z": 0.0}}, "Out-Degree": 0, "In-Degree": 1, "degree": 1}, {"label": null, "id": "Centroid", "viz": {"size": 10.714286, "position": {"y": 239.46072, "x": -543.1926, "z": 0.0}}, "Out-Degree": 0, "In-Degree": 1, "degree": 1}, {"modular": 0, "label": "angle bisector", "id": "angle bisector", "viz": {"size": 12.142857, "position": {"y": 197.84398, "x": -744.76794, "z": 0.0}}, "Out-Degree": 2, "In-Degree": 1, "degree": 3}, {"modular": 0, "label": "Congruence (geometry)", "id": "Congruence (geometry)", "viz": {"size": 11.428572, "position": {"y": 332.3964, "x": -704.4764, "z": 0.0}}, "Out-Degree": 1, "In-Degree": 1, "degree": 2}, {"modular": 0, "label": "Similarity (geometry)", "id": "Similarity (geometry)", "viz": {"size": 10.714286, "position": {"y": 583.4703, "x": -1002.10254, "z": 0.0}}, "Out-Degree": 1, "In-Degree": 0, "degree": 1}, {"modular": 0, "label": "law of sines", "id": "law of sines", "viz": {"size": 10.714286, "position": {"y": -440.32288, "x": -499.0242, "z": 0.0}}, "Out-Degree": 0, "In-Degree": 1, "degree": 1}, {"modular": 0, "label": "for any two distinct points, there is a unique line containing them", "id": "for any two distinct points, there is a unique line containing them", "viz": {"size": 10.714286, "position": {"y": -962.7203, "x": -734.7355, "z": 0.0}}, "Out-Degree": 0, "In-Degree": 1, "degree": 1}, {"modular": 0, "label": "isosceles triangle", "id": "isosceles triangle", "viz": {"size": 11.428572, "position": {"y": 418.63596, "x": -757.1302, "z": 0.0}}, "Out-Degree": 1, "In-Degree": 1, "degree": 2}, {"modular": 0, "label": "Congruence of triangles", "id": "Congruence of triangles", "viz": {"size": 13.571428, "position": {"y": 363.67975, "x": -766.11646, "z": 0.0}}, "Out-Degree": 3, "In-Degree": 2, "degree": 5}, {"modular": 0, "label": "golden ratio", "id": "golden ratio", "viz": {"size": 11.428572, "position": {"y": 1113.3367, "x": 506.26392, "z": 0.0}}, "Out-Degree": 1, "In-Degree": 1, "degree": 2}, {"modular": 1, "label": "Angle bisector theorem", "id": "Angle bisector theorem", "viz": {"size": 10.714286, "position": {"y": 324.9532, "x": -593.3808, "z": 0.0}}, "Out-Degree": 0, "In-Degree": 1, "degree": 1}, {"modular": 0, "label": "equilateral", "id": "equilateral", "viz": {"size": 10.714286, "position": {"y": 1470.4938, "x": 60.581066, "z": 0.0}}, "Out-Degree": 0, "In-Degree": 1, "degree": 1}, {"modular": 1, "label": "Vieta's formulas", "id": "Vieta's formulas", "viz": {"size": 11.428572, "position": {"y": -651.416, "x": 541.26013, "z": 0.0}}, "Out-Degree": 0, "In-Degree": 2, "degree": 2}, {"modular": 0, "label": "Power of a point", "id": "Power of a point", "viz": {"size": 10.714286, "position": {"y": 601.29193, "x": -273.88528, "z": 0.0}}, "Out-Degree": 0, "In-Degree": 1, "degree": 1}, {"modular": 0, "label": "lengths of a point on the angle bisector to each side are equal", "id": "lengths of a point on the angle bisector to each side are equal", "viz": {"size": 10.714286, "position": {"y": 169.91313, "x": -776.17816, "z": 0.0}}, "Out-Degree": 0, "In-Degree": 1, "degree": 1}, {"modular": 1, "label": "compute zeros", "id": "compute zeros", "viz": {"size": 12.857143, "position": {"y": -484.98236, "x": 625.85284, "z": 0.0}}, "Out-Degree": 3, "In-Degree": 1, "degree": 4}, {"modular": 0, "label": "features of coordinates on each axes", "id": "features of coordinates on each axes", "viz": {"size": 10.714286, "position": {"y": -881.4035, "x": 118.11291, "z": 0.0}}, "Out-Degree": 0, "In-Degree": 1, "degree": 1}, {"modular": 0, "label": "Proportionality (mathematics)", "id": "Proportionality (mathematics)", "viz": {"size": 11.428572, "position": {"y": 968.24896, "x": 672.8474, "z": 0.0}}, "Out-Degree": 1, "In-Degree": 1, "degree": 2}, {"modular": 0, "label": "full angle", "id": "full angle", "viz": {"size": 10.714286, "position": {"y": -547.62964, "x": -1040.4905, "z": 0.0}}, "Out-Degree": 0, "In-Degree": 1, "degree": 1}, {"modular": 0, "label": "twin prime conjecture", "id": "twin prime conjecture", "viz": {"size": 10.714286, "position": {"y": -96.73236, "x": 1307.352, "z": 0.0}}, "Out-Degree": 0, "In-Degree": 1, "degree": 1}, {"modular": 0, "label": "similar triangle", "id": "similar triangle", "viz": {"size": 12.142857, "position": {"y": 575.878, "x": -973.4481, "z": 0.0}}, "Out-Degree": 2, "In-Degree": 1, "degree": 3}, {"modular": 0, "label": "Circumscribed circle", "id": "Circumscribed circle", "viz": {"size": 11.428572, "position": {"y": 428.58176, "x": -439.95297, "z": 0.0}}, "Out-Degree": 0, "In-Degree": 2, "degree": 2}, {"modular": 1, "label": "greatest common divisor", "id": "greatest common divisor", "viz": {"size": 11.428572, "position": {"y": 996.7735, "x": 943.7102, "z": 0.0}}, "Out-Degree": 1, "In-Degree": 1, "degree": 2}, {"modular": 1, "label": "Chords of a Circle Theorems", "id": "Chords of a Circle Theorems", "viz": {"size": 10.714286, "position": {"y": 551.09656, "x": -220.197, "z": 0.0}}, "Out-Degree": 0, "In-Degree": 1, "degree": 1}, {"modular": 0, "label": "parallelogram", "id": "parallelogram", "viz": {"size": 12.857143, "position": {"y": 1370.4778, "x": 45.145977, "z": 0.0}}, "Out-Degree": 4, "In-Degree": 0, "degree": 4}, {"modular": 0, "label": "right angle", "id": "right angle", "viz": {"size": 11.428572, "position": {"y": -318.26044, "x": -814.9093, "z": 0.0}}, "Out-Degree": 0, "In-Degree": 2, "degree": 2}, {"modular": 0, "label": "verticality", "id": "verticality", "viz": {"size": 10.714286, "position": {"y": -756.9557, "x": -187.0585, "z": 0.0}}, "Out-Degree": 0, "In-Degree": 1, "degree": 1}, {"modular": 0, "label": "twin primes", "id": "twin primes", "viz": {"size": 11.428572, "position": {"y": -79.46071, "x": 1338.2535, "z": 0.0}}, "Out-Degree": 1, "In-Degree": 1, "degree": 2}, {"modular": 1, "label": "chord theorem", "id": "chord theorem", "viz": {"size": 10.714286, "position": {"y": 568.99316, "x": -316.29886, "z": 0.0}}, "Out-Degree": 0, "In-Degree": 1, "degree": 1}, {"modular": 0, "label": "Line (geometry)", "id": "Line (geometry)", "viz": {"size": 13.571428, "position": {"y": -976.229, "x": -713.97595, "z": 0.0}}, "Out-Degree": 5, "In-Degree": 0, "degree": 5}, {"modular": 0, "label": "Tessellation", "id": "Tessellation", "viz": {"size": 10.714286, "position": {"y": 657.4855, "x": -510.21704, "z": 0.0}}, "Out-Degree": 0, "In-Degree": 1, "degree": 1}, {"modular": 0, "label": "law of cotangents", "id": "law of cotangents", "viz": {"size": 10.714286, "position": {"y": -381.15204, "x": -601.68243, "z": 0.0}}, "Out-Degree": 0, "In-Degree": 1, "degree": 1}, {"modular": 0, "label": "judge positive or negative", "id": "judge positive or negative", "viz": {"size": 10.714286, "position": {"y": -696.1859, "x": 284.8697, "z": 0.0}}, "Out-Degree": 0, "In-Degree": 1, "degree": 1}, {"modular": 1, "label": "Spread Angle theorem", "id": "Spread Angle theorem", "viz": {"size": 10.714286, "position": {"y": 206.4361, "x": -607.3556, "z": 0.0}}, "Out-Degree": 0, "In-Degree": 1, "degree": 1}, {"modular": 0, "label": "Trigonometric functions", "id": "Trigonometric functions", "viz": {"size": 15.714286, "position": {"y": -353.16324, "x": -492.24707, "z": 0.0}}, "Out-Degree": 7, "In-Degree": 1, "degree": 8}, {"modular": 0, "label": "perpendicular bisector", "id": "perpendicular bisector", "viz": {"size": 12.142857, "position": {"y": 268.5809, "x": -770.4254, "z": 0.0}}, "Out-Degree": 2, "In-Degree": 1, "degree": 3}, {"modular": 0, "label": "trial division", "id": "trial division", "viz": {"size": 10.714286, "position": {"y": -52.121094, "x": 1514.6952, "z": 0.0}}, "Out-Degree": 0, "In-Degree": 1, "degree": 1}, {"modular": 0, "label": "Circular segment", "id": "Circular segment", "viz": {"size": 12.142857, "position": {"y": 640.2796, "x": -201.51521, "z": 0.0}}, "Out-Degree": 2, "In-Degree": 1, "degree": 3}, {"modular": 1, "label": "Thales' theorem", "id": "Thales' theorem", "viz": {"size": 11.428572, "position": {"y": 238.4479, "x": -419.65656, "z": 0.0}}, "Out-Degree": 0, "In-Degree": 2, "degree": 2}, {"modular": 0, "label": "congruence", "id": "congruence", "viz": {"size": 10.714286, "position": {"y": 256.62143, "x": -652.76807, "z": 0.0}}, "Out-Degree": 0, "In-Degree": 1, "degree": 1}, {"modular": 0, "label": "rectangle", "id": "rectangle", "viz": {"size": 17.142857, "position": {"y": 1383.0596, "x": 146.18202, "z": 0.0}}, "Out-Degree": 9, "In-Degree": 1, "degree": 10}, {"modular": 0, "label": "composite number", "id": "composite number", "viz": {"size": 10.714286, "position": {"y": 84.13303, "x": 1178.4011, "z": 0.0}}, "Out-Degree": 0, "In-Degree": 1, "degree": 1}, {"modular": 1, "label": "line segment theorem", "id": "line segment theorem", "viz": {"size": 10.714286, "position": {"y": -1066.108, "x": -730.11975, "z": 0.0}}, "Out-Degree": 0, "In-Degree": 1, "degree": 1}, {"modular": 0, "label": "law of cosines", "id": "law of cosines", "viz": {"size": 10.714286, "position": {"y": -322.0274, "x": -578.74475, "z": 0.0}}, "Out-Degree": 0, "In-Degree": 1, "degree": 1}, {"modular": 0, "label": "right triangle", "id": "right triangle", "viz": {"size": 14.285714, "position": {"y": -81.46982, "x": -596.1922, "z": 0.0}}, "Out-Degree": 4, "In-Degree": 2, "degree": 6}, {"modular": 1, "label": "Ptolemy's theorem", "id": "Ptolemy's theorem", "viz": {"size": 11.428572, "position": {"y": 734.50287, "x": -312.0109, "z": 0.0}}, "Out-Degree": 0, "In-Degree": 2, "degree": 2}, {"modular": 1, "label": "compute circumference", "id": "compute circumference", "viz": {"size": 10.714286, "position": {"y": 307.4655, "x": -555.73346, "z": 0.0}}, "Out-Degree": 0, "In-Degree": 1, "degree": 1}, {"modular": 0, "label": "natural number", "id": "natural number", "viz": {"size": 12.142857, "position": {"y": 91.19468, "x": 1199.264, "z": 0.0}}, "Out-Degree": 2, "In-Degree": 1, "degree": 3}, {"modular": 0, "label": "triangle", "id": "triangle", "viz": {"size": 30.0, "position": {"y": 263.37192, "x": -594.73016, "z": 0.0}}, "Out-Degree": 27, "In-Degree": 1, "degree": 28}, {"modular": 0, "label": "rhombus", "id": "rhombus", "viz": {"size": 12.142857, "position": {"y": 1397.0566, "x": 2.2770407, "z": 0.0}}, "Out-Degree": 2, "In-Degree": 1, "degree": 3}, {"modular": 0, "label": "vertex", "id": "vertex", "viz": {"size": 10.714286, "position": {"y": -720.21857, "x": 282.52792, "z": 0.0}}, "Out-Degree": 0, "In-Degree": 1, "degree": 1}, {"modular": 0, "label": "polynomial", "id": "polynomial", "viz": {"size": 15.0, "position": {"y": 449.69998, "x": 943.8078, "z": 0.0}}, "Out-Degree": 7, "In-Degree": 0, "degree": 7}, {"modular": 0, "label": "Elimination of variables", "id": "Elimination of variables", "viz": {"size": 10.714286, "position": {"y": -238.17137, "x": 385.14005, "z": 0.0}}, "Out-Degree": 0, "In-Degree": 1, "degree": 1}, {"modular": 0, "label": "Alternate angles", "id": "Alternate angles", "viz": {"size": 10.714286, "position": {"y": -577.943, "x": -970.98303, "z": 0.0}}, "Out-Degree": 0, "In-Degree": 1, "degree": 1}, {"modular": 1, "label": "compute gcd", "id": "compute gcd", "viz": {"size": 14.285714, "position": {"y": 1081.579, "x": 989.7854, "z": 0.0}}, "Out-Degree": 5, "In-Degree": 1, "degree": 6}, {"modular": 0, "label": "factored form", "id": "factored form", "viz": {"size": 10.714286, "position": {"y": -691.9444, "x": 265.58997, "z": 0.0}}, "Out-Degree": 0, "In-Degree": 1, "degree": 1}, {"modular": 0, "label": "least common multiple", "id": "least common multiple", "viz": {"size": 10.714286, "position": {"y": 533.0022, "x": 852.18463, "z": 0.0}}, "Out-Degree": 0, "In-Degree": 1, "degree": 1}], "directed": true, "graph": {"mode": "static", "node_default": {"Out-Degree": 0, "In-Degree": 0}, "edge_default": {}}, "multigraph": true, "links": [{"id": "1065", "key": "1065", "relationship": "proof", "source": "monotonicity", "target": "Differential calculus"}, {"id": "860", "key": "860", "relationship": "algorithm", "source": "checking the primality", "target": "Miller\u2013Rabin primality test"}, {"id": "859", "key": "859", "relationship": "algorithm", "source": "checking the primality", "target": "trial division"}, {"id": "861", "key": "861", "relationship": "algorithm", "source": "checking the primality", "target": "AKS primality test"}, {"id": "934", "key": "934", "relationship": "example", "source": "irrational number", "target": "Pi"}, {"id": "854", "key": "854", "relationship": "property", "source": "cartesian coordinate system", "target": "features of coordinates on each axes"}, {"id": "855", "key": "855", "relationship": "algorithm", "source": "cartesian coordinate system", "target": "compute line segment that parallel axes: big coordinates - small coordinates"}, {"id": "857", "key": "857", "relationship": "algorithm", "source": "cartesian coordinate system", "target": "compute coordinates of symmetric points"}, {"id": "856", "key": "856", "relationship": "algorithm", "source": "cartesian coordinate system", "target": "compute the area of a polygon in a plane: cutting method"}, {"id": "853", "key": "853", "relationship": "property", "source": "cartesian coordinate system", "target": "features of coordinates in each quadrant"}, {"id": "985", "key": "985", "relationship": "expression", "source": "quadratic function", "target": "vertex form"}, {"id": "986", "key": "986", "relationship": "property", "source": "quadratic function", "target": "opening direction and scale of a function"}, {"id": "984", "key": "984", "relationship": "expression", "source": "quadratic function", "target": "factored form"}, {"id": "987", "key": "987", "relationship": "property", "source": "quadratic function", "target": "symmetry"}, {"id": "983", "key": "983", "relationship": "expression", "source": "quadratic function", "target": "standard form"}, {"id": "989", "key": "989", "relationship": "property", "source": "quadratic function", "target": "vertex"}, {"id": "982", "key": "982", "relationship": "expression", "source": "quadratic function", "target": "diagrammatic sketch"}, {"id": "991", "key": "991", "relationship": "corollary", "source": "quadratic function", "target": "judge positive or negative"}, {"id": "990", "key": "990", "relationship": "property", "source": "quadratic function", "target": "maximum and minimum value"}, {"id": "1071", "key": "1071", "relationship": "property", "source": "quadratic function", "target": "Zero of a function"}, {"id": "988", "key": "988", "relationship": "property", "source": "quadratic function", "target": "monotonicity"}, {"id": "1108", "key": "1108", "relationship": "application", "source": "Inequation", "target": "Triangle inequality"}, {"id": "923", "key": "923", "relationship": "contain", "source": "Inequation", "target": "System of Linear Inequalities with one unknown"}, {"id": "1068", "key": "1068", "relationship": "formula", "source": "Inequation", "target": "Inequality of arithmetic and geometric means"}, {"id": "922", "key": "922", "relationship": "contain", "source": "Inequation", "target": "linear ineqality with one unknown"}, {"id": "1034", "key": "1034", "relationship": "contain", "source": "Transformation (function)", "target": "Linear map"}, {"id": "1033", "key": "1033", "relationship": "contain", "source": "Transformation (function)", "target": "Affine transformation"}, {"id": "1030", "key": "1030", "relationship": "contain", "source": "Transformation (function)", "target": "Reflection"}, {"id": "1031", "key": "1031", "relationship": "contain", "source": "Transformation (function)", "target": "Rotation (mathematics)"}, {"id": "1029", "key": "1029", "relationship": "contain", "source": "Transformation (function)", "target": "Homothetic transformation"}, {"id": "1032", "key": "1032", "relationship": "contain", "source": "Transformation (function)", "target": "Translation (geometry)"}, {"id": "1020", "key": "1020", "relationship": "property", "source": "square", "target": "convex"}, {"id": "1023", "key": "1023", "relationship": "property", "source": "square", "target": "isogonal"}, {"id": "1024", "key": "1024", "relationship": "property", "source": "square", "target": "isotoxal"}, {"id": "1022", "key": "1022", "relationship": "property", "source": "square", "target": "equilateral"}, {"id": "1021", "key": "1021", "relationship": "property", "source": "square", "target": "cyclic"}, {"id": "953", "key": "953", "relationship": "theorem", "source": "Parallel (geometry)", "target": "Parallel postulate"}, {"id": "1019", "key": "1019", "relationship": "theorem", "source": "sine", "target": "law of sines"}, {"id": "850", "key": "850", "relationship": "theorem", "source": "binomial", "target": "binomial theorem"}, {"id": "851", "key": "851", "relationship": "formula", "source": "binomial", "target": "Difference of two squares"}, {"id": "896", "key": "896", "relationship": "theorem", "source": "cotangent", "target": "law of cotangents"}, {"id": "1070", "key": "1070", "relationship": "application", "source": "Zero of a function", "target": "compute zeros"}, {"id": "1077", "key": "1077", "relationship": "formula", "source": "Zero of a function", "target": "Vieta's formulas"}, {"id": "842", "key": "842", "relationship": "expression", "source": "angle", "target": "Degree (angle)"}, {"id": "836", "key": "836", "relationship": "contain", "source": "angle", "target": "acute angles"}, {"id": "840", "key": "840", "relationship": "contain", "source": "angle", "target": "full angle"}, {"id": "845", "key": "845", "relationship": "property", "source": "angle", "target": "Interior angles on the same side"}, {"id": "843", "key": "843", "relationship": "property", "source": "angle", "target": "Corresponding angles"}, {"id": "841", "key": "841", "relationship": "expression", "source": "angle", "target": "Radian"}, {"id": "839", "key": "839", "relationship": "contain", "source": "angle", "target": "straight angle"}, {"id": "846", "key": "846", "relationship": "property", "source": "angle", "target": "vertical angles"}, {"id": "837", "key": "837", "relationship": "contain", "source": "angle", "target": "right angle"}, {"id": "847", "key": "847", "relationship": "property", "source": "angle", "target": "supplementary angles"}, {"id": "844", "key": "844", "relationship": "property", "source": "angle", "target": "Alternate angles"}, {"id": "838", "key": "838", "relationship": "contain", "source": "angle", "target": "obtuse angles"}, {"id": "994", "key": "994", "relationship": "contain", "source": "rational number", "target": "integer"}, {"id": "893", "key": "893", "relationship": "formula", "source": "Cone", "target": "lateral surface area"}, {"id": "894", "key": "894", "relationship": "formula", "source": "Cone", "target": "total surface area"}, {"id": "880", "key": "880", "relationship": "contain", "source": "complex number", "target": "imaginary number"}, {"id": "882", "key": "882", "relationship": "arithmetic operation", "source": "complex number", "target": "addition"}, {"id": "883", "key": "883", "relationship": "arithmetic operation", "source": "complex number", "target": "subtraction"}, {"id": "885", "key": "885", "relationship": "arithmetic operation", "source": "complex number", "target": "division"}, {"id": "879", "key": "879", "relationship": "contain", "source": "complex number", "target": "real number"}, {"id": "881", "key": "881", "relationship": "contain", "source": "complex number", "target": "Gaussian integer"}, {"id": "884", "key": "884", "relationship": "arithmetic operation", "source": "complex number", "target": "multiplication"}, {"id": "993", "key": "993", "relationship": "contain", "source": "Quadrilateral", "target": "Parallelogram"}, {"id": "992", "key": "992", "relationship": "contain", "source": "Quadrilateral", "target": "Trapezoid"}, {"id": "1101", "key": "1101", "relationship": "algorithm", "source": "Quadrilateral", "target": "Ptolemy's theorem"}, {"id": "1079", "key": "1079", "relationship": "example", "source": "compute poles", "target": "compute maximum or minimum"}, {"id": "905", "key": "905", "relationship": "algorithm", "source": "factorization", "target": "FOIL method"}, {"id": "906", "key": "906", "relationship": "algorithm", "source": "factorization", "target": "binomial theorem"}, {"id": "907", "key": "907", "relationship": "algorithm", "source": "factorization", "target": "Difference of two squares"}, {"id": "980", "key": "980", "relationship": "algorithm", "source": "quadratic equation", "target": "Completing the square"}, {"id": "979", "key": "979", "relationship": "algorithm", "source": "quadratic equation", "target": "factorization"}, {"id": "981", "key": "981", "relationship": "property", "source": "quadratic equation", "target": "discriminant of the quadratic equation"}, {"id": "978", "key": "978", "relationship": "algorithm", "source": "quadratic equation", "target": "Quadratic formula"}, {"id": "1035", "key": "1035", "relationship": "property", "source": "Trapezoid", "target": "convex"}, {"id": "1036", "key": "1036", "relationship": "contain", "source": "Trapezoid", "target": "isosceles trapezoid"}, {"id": "1028", "key": "1028", "relationship": "theorem", "source": "tangent", "target": "law of tangents"}, {"id": "950", "key": "950", "relationship": "contain", "source": "multiplication", "target": "multiple"}, {"id": "899", "key": "899", "relationship": "contain", "source": "divisor", "target": "greatest common divisor"}, {"id": "852", "key": "852", "relationship": "proof", "source": "B\u00e9zout's identity", "target": "euclid's theorem"}, {"id": "1027", "key": "1027", "relationship": "algorithm", "source": "System of 2 linear equations with 2 unknowns", "target": "Row reduction"}, {"id": "1026", "key": "1026", "relationship": "algorithm", "source": "System of 2 linear equations with 2 unknowns", "target": "Elimination of variables"}, {"id": "927", "key": "927", "relationship": "property", "source": "Intersection (Euclidean geometry)", "target": "vertical angles"}, {"id": "926", "key": "926", "relationship": "algorithm", "source": "Intersection (Euclidean geometry)", "target": "compute intersection"}, {"id": "995", "key": "995", "relationship": "contain", "source": "real number", "target": "rational number"}, {"id": "996", "key": "996", "relationship": "contain", "source": "real number", "target": "irrational number"}, {"id": "1059", "key": "1059", "relationship": "theorem", "source": "vertical angles", "target": "vertical angle theorem"}, {"id": "943", "key": "943", "relationship": "expression", "source": "linear function (calculus)", "target": "slope-intercept form"}, {"id": "948", "key": "948", "relationship": "property", "source": "linear function (calculus)", "target": "positive and negative property"}, {"id": "946", "key": "946", "relationship": "property", "source": "linear function (calculus)", "target": "verticality"}, {"id": "947", "key": "947", "relationship": "algorithm", "source": "linear function (calculus)", "target": "compute intersection"}, {"id": "945", "key": "945", "relationship": "property", "source": "linear function (calculus)", "target": "translational property"}, {"id": "944", "key": "944", "relationship": "property", "source": "linear function (calculus)", "target": "monotonicity"}, {"id": "864", "key": "864", "relationship": "contain", "source": "Circle", "target": "Circular segment"}, {"id": "873", "key": "873", "relationship": "contain", "source": "Circle", "target": "chord tangent angle"}, {"id": "869", "key": "869", "relationship": "arithmetic operation", "source": "Circle", "target": "central angle"}, {"id": "871", "key": "871", "relationship": "property", "source": "Circle", "target": "secant"}, {"id": "866", "key": "866", "relationship": "property", "source": "Circle", "target": "Point reflection"}, {"id": "1087", "key": "1087", "relationship": "example", "source": "Circle", "target": "Circumscribed circle"}, {"id": "863", "key": "863", "relationship": "property", "source": "Circle", "target": "Reflectional symmetry"}, {"id": "872", "key": "872", "relationship": "property", "source": "Circle", "target": "tangent(circle)"}, {"id": "865", "key": "865", "relationship": "theorem", "source": "Circle", "target": "Chords of a Circle Theorems"}, {"id": "868", "key": "868", "relationship": "contain", "source": "Circle", "target": "inscribed angle"}, {"id": "867", "key": "867", "relationship": "theorem", "source": "Circle", "target": "Thales' theorem"}, {"id": "1100", "key": "1100", "relationship": "algorithm", "source": "Circle", "target": "Ptolemy's theorem"}, {"id": "875", "key": "875", "relationship": "formula", "source": "Circle", "target": "area of the sector"}, {"id": "870", "key": "870", "relationship": "theorem", "source": "Circle", "target": "chord theorem"}, {"id": "1088", "key": "1088", "relationship": "example", "source": "Circle", "target": "Incircle and excircles of a triangle"}, {"id": "874", "key": "874", "relationship": "theorem", "source": "Circle", "target": "Power of a point"}, {"id": "876", "key": "876", "relationship": "formula", "source": "Circle", "target": "length of the arc"}, {"id": "834", "key": "834", "relationship": "arithmetic operation", "source": "Algebraic fraction", "target": "multiplication"}, {"id": "832", "key": "832", "relationship": "arithmetic operation", "source": "Algebraic fraction", "target": "addition"}, {"id": "833", "key": "833", "relationship": "arithmetic operation", "source": "Algebraic fraction", "target": "subtraction"}, {"id": "835", "key": "835", "relationship": "arithmetic operation", "source": "Algebraic fraction", "target": "division"}, {"id": "897", "key": "897", "relationship": "contain", "source": "division", "target": "divisor"}, {"id": "898", "key": "898", "relationship": "expression", "source": "division", "target": "Proportionality (mathematics)"}, {"id": "975", "key": "975", "relationship": "property", "source": "prime number", "target": "coprime numbers"}, {"id": "974", "key": "974", "relationship": "theorem", "source": "prime number", "target": "euclid's theorem"}, {"id": "972", "key": "972", "relationship": "theorem", "source": "prime number", "target": "euclid's theorem"}, {"id": "970", "key": "970", "relationship": "application", "source": "prime number", "target": "checking the primality"}, {"id": "969", "key": "969", "relationship": "theorem", "source": "prime number", "target": "prime number theorem"}, {"id": "971", "key": "971", "relationship": "conjecture", "source": "prime number", "target": "Goldbach's conjecture"}, {"id": "976", "key": "976", "relationship": "theorem", "source": "prime number", "target": "fundamental theorem of arithmetic"}, {"id": "973", "key": "973", "relationship": "contain", "source": "prime number", "target": "twin primes"}, {"id": "925", "key": "925", "relationship": "application", "source": "integer", "target": "factorization"}, {"id": "924", "key": "924", "relationship": "contain", "source": "integer", "target": "natural number"}, {"id": "928", "key": "928", "relationship": "expression", "source": "inverse proportional function", "target": "inverse proportional form"}, {"id": "933", "key": "933", "relationship": "algorithm", "source": "inverse proportional function", "target": "compute intersection"}, {"id": "931", "key": "931", "relationship": "property", "source": "inverse proportional function", "target": "symmetry"}, {"id": "929", "key": "929", "relationship": "property", "source": "inverse proportional function", "target": "regional property"}, {"id": "932", "key": "932", "relationship": "property", "source": "inverse proportional function", "target": "area only related to k"}, {"id": "930", "key": "930", "relationship": "property", "source": "inverse proportional function", "target": "monotonicity"}, {"id": "895", "key": "895", "relationship": "theorem", "source": "cosine", "target": "law of cosines"}, {"id": "949", "key": "949", "relationship": "contain", "source": "multiple", "target": "least common multiple"}, {"id": "920", "key": "920", "relationship": "proof methods", "source": "fundamental theorem of arithmetic", "target": "induction"}, {"id": "1067", "key": "1067", "relationship": "algorithm", "source": "compute maximum or minimum", "target": "Differential calculus"}, {"id": "1069", "key": "1069", "relationship": "algorithm", "source": "compute maximum or minimum", "target": "Inequality of arithmetic and geometric means"}, {"id": "902", "key": "902", "relationship": "contain", "source": "Equation", "target": "System of 2 linear equations with 2 unknowns"}, {"id": "903", "key": "903", "relationship": "contain", "source": "Equation", "target": "quadratic equation"}, {"id": "901", "key": "901", "relationship": "contain", "source": "Equation", "target": "Fraction equation"}, {"id": "900", "key": "900", "relationship": "contain", "source": "Equation", "target": "one variable linear equation"}, {"id": "936", "key": "936", "relationship": "formula", "source": "length of the arc", "target": "Pi"}, {"id": "862", "key": "862", "relationship": "theorem", "source": "chord tangent angle", "target": "Alternate Segment Theorem"}, {"id": "916", "key": "916", "relationship": "contain", "source": "Function (mathematics)", "target": "quadratic function"}, {"id": "910", "key": "910", "relationship": "application", "source": "Function (mathematics)", "target": "compute intersection"}, {"id": "911", "key": "911", "relationship": "application", "source": "Function (mathematics)", "target": "compute area"}, {"id": "909", "key": "909", "relationship": "application", "source": "Function (mathematics)", "target": "compute function expression"}, {"id": "917", "key": "917", "relationship": "contain", "source": "Function (mathematics)", "target": "power function"}, {"id": "1060", "key": "1060", "relationship": "expression", "source": "Function (mathematics)", "target": "Equation"}, {"id": "919", "key": "919", "relationship": "property", "source": "Function (mathematics)", "target": "Transformation (function)"}, {"id": "915", "key": "915", "relationship": "contain", "source": "Function (mathematics)", "target": "inverse proportional function"}, {"id": "1064", "key": "1064", "relationship": "application", "source": "Function (mathematics)", "target": "compute maximum or minimum"}, {"id": "914", "key": "914", "relationship": "contain", "source": "Function (mathematics)", "target": "linear function (calculus)"}, {"id": "912", "key": "912", "relationship": "application", "source": "Function (mathematics)", "target": "compare value of functions"}, {"id": "918", "key": "918", "relationship": "contain", "source": "Function (mathematics)", "target": "Trigonometric functions"}, {"id": "913", "key": "913", "relationship": "contain", "source": "Function (mathematics)", "target": "cartesian coordinate system"}, {"id": "1089", "key": "1089", "relationship": "formula", "source": "compute area", "target": "Heron's formula"}, {"id": "886", "key": "886", "relationship": "contain", "source": "compute area", "target": "lateral surface area"}, {"id": "887", "key": "887", "relationship": "contain", "source": "compute area", "target": "total surface area"}, {"id": "858", "key": "858", "relationship": "contain", "source": "cartesian product", "target": "Function (mathematics)"}, {"id": "904", "key": "904", "relationship": "proof", "source": "euclid's lemma", "target": "fundamental theorem of arithmetic"}, {"id": "1063", "key": "1063", "relationship": "algorithm", "source": "compute function expression", "target": "substitution"}, {"id": "908", "key": "908", "relationship": "application", "source": "Fraction equation", "target": "Extraneous and missing solutions"}, {"id": "1076", "key": "1076", "relationship": "formula", "source": "coefficients of a polynomial", "target": "Vieta's formulas"}, {"id": "1012", "key": "1012", "relationship": "arithmetic operation", "source": "Set (mathematics)", "target": "Intersection"}, {"id": "1010", "key": "1010", "relationship": "contain", "source": "Set (mathematics)", "target": "subset"}, {"id": "1014", "key": "1014", "relationship": "arithmetic operation", "source": "Set (mathematics)", "target": "cartesian product"}, {"id": "1013", "key": "1013", "relationship": "arithmetic operation", "source": "Set (mathematics)", "target": "complement"}, {"id": "1015", "key": "1015", "relationship": "expression", "source": "Set (mathematics)", "target": "Venn diagram"}, {"id": "1011", "key": "1011", "relationship": "arithmetic operation", "source": "Set (mathematics)", "target": "union"}, {"id": "1073", "key": "1073", "relationship": "corollary", "source": "Intermediate value theorem", "target": "Bolzano's theorem"}, {"id": "942", "key": "942", "relationship": "theorem", "source": "Line segment", "target": "line segment theorem"}, {"id": "960", "key": "960", "relationship": "contain", "source": "Polygon", "target": "Quadrilateral"}, {"id": "1104", "key": "1104", "relationship": "application", "source": "Polygon", "target": "Tessellation"}, {"id": "961", "key": "961", "relationship": "contain", "source": "Polygon", "target": "Regular polygon"}, {"id": "959", "key": "959", "relationship": "contain", "source": "Polygon", "target": "triangle"}, {"id": "1080", "key": "1080", "relationship": "application", "source": "Integral", "target": "compute area"}, {"id": "1081", "key": "1081", "relationship": "theorem", "source": "Integral", "target": "Fundamental theorem of calculus"}, {"id": "1082", "key": "1082", "relationship": "theorem", "source": "Derivative", "target": "Fundamental theorem of calculus"}, {"id": "1078", "key": "1078", "relationship": "application", "source": "Derivative", "target": "Differential calculus"}, {"id": "1025", "key": "1025", "relationship": "property", "source": "straight angle", "target": "supplementary angle"}, {"id": "848", "key": "848", "relationship": "property", "source": "angle bisector", "target": "lengths of a point on the angle bisector to each side are equal"}, {"id": "849", "key": "849", "relationship": "contain", "source": "angle bisector", "target": "center of incircle"}, {"id": "1092", "key": "1092", "relationship": "contain", "source": "Congruence (geometry)", "target": "Congruence of triangles"}, {"id": "1018", "key": "1018", "relationship": "contain", "source": "Similarity (geometry)", "target": "similar triangle"}, {"id": "935", "key": "935", "relationship": "contain", "source": "isosceles triangle", "target": "equilateral triangle"}, {"id": "1094", "key": "1094", "relationship": "algorithm", "source": "Congruence of triangles", "target": "SAS (Side-Angle-Side)"}, {"id": "1096", "key": "1096", "relationship": "algorithm", "source": "Congruence of triangles", "target": "ASA (Angle-Side-Angle)"}, {"id": "1095", "key": "1095", "relationship": "algorithm", "source": "Congruence of triangles", "target": "SSS (Side-Side-Side)"}, {"id": "1103", "key": "1103", "relationship": "application", "source": "golden ratio", "target": "Golden rectangle"}, {"id": "1072", "key": "1072", "relationship": "algorithm", "source": "compute zeros", "target": "Bisection method"}, {"id": "1074", "key": "1074", "relationship": "algorithm", "source": "compute zeros", "target": "Bolzano's theorem"}, {"id": "1075", "key": "1075", "relationship": "algorithm", "source": "compute zeros", "target": "Quadratic formula"}, {"id": "977", "key": "977", "relationship": "example", "source": "Proportionality (mathematics)", "target": "golden ratio"}, {"id": "1016", "key": "1016", "relationship": "contain", "source": "similar triangle", "target": "equilateral triangle"}, {"id": "1017", "key": "1017", "relationship": "theorem", "source": "similar triangle", "target": "Intercept theorem"}, {"id": "921", "key": "921", "relationship": "application", "source": "greatest common divisor", "target": "compute gcd"}, {"id": "956", "key": "956", "relationship": "property", "source": "parallelogram", "target": "convex"}, {"id": "954", "key": "954", "relationship": "contain", "source": "parallelogram", "target": "rectangle"}, {"id": "955", "key": "955", "relationship": "contain", "source": "parallelogram", "target": "rhombus"}, {"id": "1109", "key": "1109", "relationship": "theorem", "source": "parallelogram", "target": "Theorem of the gnomon"}, {"id": "1058", "key": "1058", "relationship": "conjecture", "source": "twin primes", "target": "twin prime conjecture"}, {"id": "939", "key": "939", "relationship": "property", "source": "Line (geometry)", "target": "Intersection (Euclidean geometry)"}, {"id": "937", "key": "937", "relationship": "theorem", "source": "Line (geometry)", "target": "for any two distinct points, there is a unique line containing them"}, {"id": "938", "key": "938", "relationship": "property", "source": "Line (geometry)", "target": "Perpendicular"}, {"id": "940", "key": "940", "relationship": "contain", "source": "Line (geometry)", "target": "Line segment"}, {"id": "941", "key": "941", "relationship": "property", "source": "Line (geometry)", "target": "Parallel (geometry)"}, {"id": "1052", "key": "1052", "relationship": "contain", "source": "Trigonometric functions", "target": "sine"}, {"id": "1055", "key": "1055", "relationship": "application", "source": "Trigonometric functions", "target": "right triangle"}, {"id": "1056", "key": "1056", "relationship": "contain", "source": "Trigonometric functions", "target": "cotangent"}, {"id": "1053", "key": "1053", "relationship": "contain", "source": "Trigonometric functions", "target": "cosine"}, {"id": "1066", "key": "1066", "relationship": "property", "source": "Trigonometric functions", "target": "periodicity"}, {"id": "1057", "key": "1057", "relationship": "theorem", "source": "Trigonometric functions", "target": "Pythagorean theorem"}, {"id": "1054", "key": "1054", "relationship": "contain", "source": "Trigonometric functions", "target": "tangent"}, {"id": "957", "key": "957", "relationship": "property", "source": "perpendicular bisector", "target": "circumcenter"}, {"id": "958", "key": "958", "relationship": "property", "source": "perpendicular bisector", "target": "lengths of a point on the perpendicular bisector to each vertex are equal"}, {"id": "878", "key": "878", "relationship": "theorem", "source": "Circular segment", "target": "Intersecting Chords Theorem"}, {"id": "877", "key": "877", "relationship": "property", "source": "Circular segment", "target": "Reflectional symmetry"}, {"id": "999", "key": "999", "relationship": "property", "source": "rectangle", "target": "isogonal"}, {"id": "1004", "key": "1004", "relationship": "theorem", "source": "rectangle", "target": "British flag theorem"}, {"id": "1102", "key": "1102", "relationship": "example", "source": "rectangle", "target": "Golden rectangle"}, {"id": "1003", "key": "1003", "relationship": "theorem", "source": "rectangle", "target": "Japanese theorem for cyclic quadrilaterals"}, {"id": "1000", "key": "1000", "relationship": "property", "source": "rectangle", "target": "cyclic"}, {"id": "1001", "key": "1001", "relationship": "property", "source": "rectangle", "target": "quailateral"}, {"id": "998", "key": "998", "relationship": "property", "source": "rectangle", "target": "convex"}, {"id": "997", "key": "997", "relationship": "contain", "source": "rectangle", "target": "square"}, {"id": "1002", "key": "1002", "relationship": "theorem", "source": "rectangle", "target": "isopermetric theorem"}, {"id": "1009", "key": "1009", "relationship": "property", "source": "right triangle", "target": "right angle"}, {"id": "1008", "key": "1008", "relationship": "theorem", "source": "right triangle", "target": "Thales' theorem"}, {"id": "1007", "key": "1007", "relationship": "theorem", "source": "right triangle", "target": "Pythagorean theorem"}, {"id": "1083", "key": "1083", "relationship": "theorem", "source": "right triangle", "target": "right triangle altitude theorem"}, {"id": "952", "key": "952", "relationship": "contain", "source": "natural number", "target": "composite number"}, {"id": "951", "key": "951", "relationship": "contain", "source": "natural number", "target": "prime number"}, {"id": "1099", "key": "1099", "relationship": "theorem", "source": "triangle", "target": "Ceva's theorem"}, {"id": "1098", "key": "1098", "relationship": "theorem", "source": "triangle", "target": "Menelaus's theorem"}, {"id": "1041", "key": "1041", "relationship": "contain", "source": "triangle", "target": "obtuse triangle"}, {"id": "1040", "key": "1040", "relationship": "contain", "source": "triangle", "target": "acute triangle"}, {"id": "1085", "key": "1085", "relationship": "property", "source": "triangle", "target": "Circumscribed circle"}, {"id": "1042", "key": "1042", "relationship": "property", "source": "triangle", "target": "conditions on the sides"}, {"id": "1045", "key": "1045", "relationship": "property", "source": "triangle", "target": "conditions on the sides"}, {"id": "1084", "key": "1084", "relationship": "property", "source": "triangle", "target": "Centroid"}, {"id": "1046", "key": "1046", "relationship": "property", "source": "triangle", "target": "median"}, {"id": "1086", "key": "1086", "relationship": "property", "source": "triangle", "target": "Incircle and excircles of a triangle"}, {"id": "1105", "key": "1105", "relationship": "theorem", "source": "triangle", "target": "Spread Angle theorem"}, {"id": "1047", "key": "1047", "relationship": "property", "source": "triangle", "target": "angle bisector"}, {"id": "1091", "key": "1091", "relationship": "property", "source": "triangle", "target": "Congruence (geometry)"}, {"id": "1050", "key": "1050", "relationship": "property", "source": "triangle", "target": "perpendicular bisector"}, {"id": "1107", "key": "1107", "relationship": "property", "source": "triangle", "target": "Triangle inequality"}, {"id": "1043", "key": "1043", "relationship": "algorithm", "source": "triangle", "target": "compute area"}, {"id": "1037", "key": "1037", "relationship": "contain", "source": "triangle", "target": "isosceles triangle"}, {"id": "1093", "key": "1093", "relationship": "application", "source": "triangle", "target": "Congruence of triangles"}, {"id": "1039", "key": "1039", "relationship": "contain", "source": "triangle", "target": "right triangle"}, {"id": "1097", "key": "1097", "relationship": "theorem", "source": "triangle", "target": "Angle bisector theorem"}, {"id": "1044", "key": "1044", "relationship": "algorithm", "source": "triangle", "target": "compute circumference"}, {"id": "1048", "key": "1048", "relationship": "property", "source": "triangle", "target": "altitude"}, {"id": "1049", "key": "1049", "relationship": "property", "source": "triangle", "target": "mid-segment line"}, {"id": "1106", "key": "1106", "relationship": "property", "source": "triangle", "target": "Euler line"}, {"id": "1090", "key": "1090", "relationship": "formula", "source": "triangle", "target": "Heron's formula"}, {"id": "1038", "key": "1038", "relationship": "contain", "source": "triangle", "target": "scalene triangle"}, {"id": "1051", "key": "1051", "relationship": "property", "source": "triangle", "target": "congruence"}, {"id": "1005", "key": "1005", "relationship": "property", "source": "rhombus", "target": "convex"}, {"id": "1006", "key": "1006", "relationship": "property", "source": "rhombus", "target": "isotoxal"}, {"id": "965", "key": "965", "relationship": "arithmetic operation", "source": "polynomial", "target": "expoentiation"}, {"id": "968", "key": "968", "relationship": "application", "source": "polynomial", "target": "factorization"}, {"id": "963", "key": "963", "relationship": "arithmetic operation", "source": "polynomial", "target": "subtraction"}, {"id": "966", "key": "966", "relationship": "formula", "source": "polynomial", "target": "Difference of two squares"}, {"id": "967", "key": "967", "relationship": "contain", "source": "polynomial", "target": "binomial"}, {"id": "964", "key": "964", "relationship": "arithmetic operation", "source": "polynomial", "target": "multiplication"}, {"id": "962", "key": "962", "relationship": "arithmetic operation", "source": "polynomial", "target": "addition"}, {"id": "889", "key": "889", "relationship": "algorithm", "source": "compute gcd", "target": "euclidean algorithm"}, {"id": "890", "key": "890", "relationship": "algorithm", "source": "compute gcd", "target": "lehmer's gcd algorithm"}, {"id": "888", "key": "888", "relationship": "algorithm", "source": "compute gcd", "target": "prime factorization"}, {"id": "891", "key": "891", "relationship": "algorithm", "source": "compute gcd", "target": "binary gcd algorithm"}, {"id": "892", "key": "892", "relationship": "proof methods", "source": "compute gcd", "target": "exhaustion"}]}